MANIFEST.in
README.rst
setup.py
docs/HISTORY.txt
docs/LICENSE.GPL
docs/LICENSE.txt
ftw/__init__.py
ftw.publisher.receiver.egg-info/PKG-INFO
ftw.publisher.receiver.egg-info/SOURCES.txt
ftw.publisher.receiver.egg-info/dependency_links.txt
ftw.publisher.receiver.egg-info/entry_points.txt
ftw.publisher.receiver.egg-info/namespace_packages.txt
ftw.publisher.receiver.egg-info/not-zip-safe
ftw.publisher.receiver.egg-info/requires.txt
ftw.publisher.receiver.egg-info/top_level.txt
ftw/publisher/__init__.py
ftw/publisher/receiver/__init__.py
ftw/publisher/receiver/configure.zcml
ftw/publisher/receiver/decoder.py
ftw/publisher/receiver/eventhandlers.py
ftw/publisher/receiver/events.py
ftw/publisher/receiver/helpers.py
ftw/publisher/receiver/interfaces.py
ftw/publisher/receiver/testing.py
ftw/publisher/receiver/browser/__init__.py
ftw/publisher/receiver/browser/configure.zcml
ftw/publisher/receiver/browser/views.py
ftw/publisher/receiver/tests/__init__.py
ftw/publisher/receiver/tests/builders.py
ftw/publisher/receiver/tests/helpers.py
ftw/publisher/receiver/tests/test_decoder.py
ftw/publisher/receiver/tests/test_events.py
ftw/publisher/receiver/tests/test_getData.py
ftw/publisher/receiver/tests/test_integration.py
ftw/publisher/receiver/tests/assets/basic_folder.json
ftw/publisher/receiver/tests/assets/basic_folder_dx.json
ftw/publisher/receiver/tests/assets/image.json
ftw/publisher/receiver/tests/assets/image_dx.json
ftw/publisher/receiver/tests/assets/move_image.json
ftw/publisher/receiver/tests/assets/plonesite.json