Metadata-Version: 2.1
Name: ftw.publisher.receiver
Version: 2.3.1
Summary: Staging and publishing addon for Plone contents.
Home-page: https://github.com/4teamwork/ftw.publisher.receiver
Author: 4teamwork AG
Author-email: mailto:info@4teamwork.ch
License: GPL2
Keywords: ftw publisher receiver
Platform: UNKNOWN
Classifier: Framework :: Plone
Classifier: Framework :: Plone :: 4.3
Classifier: Framework :: Plone :: 5.1
Classifier: Programming Language :: Python
Classifier: Topic :: Software Development :: Libraries :: Python Modules
Provides-Extra: PloneFormGen
Provides-Extra: tests
Provides-Extra: tests_plone4
